{
  "type": "biotech:greenhouse",
  "itemInputs": [
    {
      "itemStack": {
        "id": "carrot",
        "Count": 2
      },
      "isConsumable": true
    },
    {
      "itemStack": {
        "id": "biotech:fertilizer",
        "Count": 2
      },
      "isConsumable": true
    }
  ],
  "itemOutputs": [
    {
      "itemStack": {
        "id": "carrot",
        "Count": 12
      },
      "chance": 1.0
    }
  ],
  "fluidInputs": [
    {
      "FluidName": "minecraft:water",
      "Amount": 500
    }
  ],
  "fluidOutputs": [],
  "energy": 160000
}